lookatme/contrib/render.py
lookatme.contrib.render-1.1.0.dist-info/LICENSE
lookatme.contrib.render-1.1.0.dist-info/METADATA
lookatme.contrib.render-1.1.0.dist-info/WHEEL
lookatme.contrib.render-1.1.0.dist-info/top_level.txt
lookatme.contrib.render-1.1.0.dist-info/RECORD
